{"id":"10046","name":"Pressmaster.ai","description":"AI platform for creating and distributing thought leadership content.","category":"ai-marketing","url":"http://www.pressmaster.ai?afmc=1n","rating":5.0,"monthly_visits":49974,"pricing":{"type":"freemium"},"tags":["AI Writing","Social media management","Thought leadership","AI Repurpose","Content automation","AI content creation","AI Social Media","AI Summarizer","AI Social Media Post Generator","AI Productivity Tools","Press release distribution","PR tool","AI Plagiarism Checker","Trend analysis","AI Blog Generator","AI Assistant","Content repurposing","AI Marketing"],"features":["Pricing","Features","automation","ai_powered"]}