{"id":"10255","name":"Univerbal (formerly Quazel)","description":"AI language tutor for fluent, natural conversations and personalized learning.","category":"ai-language-learning","url":"https://www.univerbal.app","rating":5.0,"monthly_visits":12527,"pricing":{"type":"free-trial"},"tags":["AI Speech-to-Text","AI language learning","Language education","Language tutor","AI Chatbot","Fluency","Conversational practice","Language skills","AI chatbot","Personalized learning","AI Language Learning","AI Text-to-Speech","AI Assistant"],"features":["Features","chatbot","education","speech_ai","Pricing","ai_powered"]}