{"id":"10419","name":"RssPal","description":"AI-powered RSS feed generator for personalized news and updates.","category":"ai-summarizer","url":"https://rsspal.io","rating":5.0,"monthly_visits":0,"pricing":{"type":"contact-for-pricing"},"tags":["News aggregator","AI News","AI Social Media","Information management","AI Summarizer","AI Translate","Podcast feeds","AI translation","Social media feeds","Content monitoring","RSS feed generator","AI Article Summarizer"],"features":["Pricing","Features","ai_powered"]}