{"id":"10467","name":"RightResponse AI","description":"AI-powered review management for location-based businesses.","category":"ai-response-generator","url":"https://www.rightresponseai.com","rating":5.0,"monthly_visits":4035,"pricing":{"type":"free-trial"},"tags":["Multi-location Business","AI","Competitor Analysis","Google Review Management","Sentiment Analysis","Review Response Automation","Customer Retention","AI Workflows","SaaS","Review Management","Brand Loyalty","Map Rankings","Customer Acquisition","AI Response Generator","Local SEO","Google Maps Rank Tracker","Customer Feedback","AI Customer Service","AI SEO Tools","Generative AI","Review Requests","Reputation Management"],"features":["Features","subscription","automation","ai_powered","web_based","Pricing","business","saas"]}