{"id":"10955","name":"mappedin.com","description":"Mappedin is an indoor mapping platform with AI tools for creating and sharing maps.","category":"ai-map-generator","url":"https://mappedin.com","rating":5.0,"monthly_visits":112959,"pricing":{"type":"freemium"},"tags":["AI Map Generator","AI mapping","Developer tools","AI 3D Model Generator","Real-time data integration","Location analytics","AI Floor Plan Generator","Wayfinding","3D maps","Indoor mapping","Navigation"],"features":["Features","real_time","ai_powered","analytics","Pricing","developer"]}