{"id":"11108","name":"StylerAI Wardrobe App","description":"AI-powered wardrobe management app with style suggestions and organization tools.","category":"ai-outfit-generator","url":"https://apps.apple.com/us/app/stylerai/id6476791031","rating":5.0,"monthly_visits":0,"pricing":{"type":"free"},"tags":["Background removal","AI fashion","Outfit recommendations","Style suggestions","Personal stylist","AI Description Generator","Wardrobe management","Fashion AI","Clothing categorization","AI Outfit Generator","AI Background Remover","Fashion app"],"features":["Pricing","Features","ai_powered"]}