{"id":"11456","name":"Gemini AI for Sheets","description":"AI-powered Google Sheets add-on for automation and enhanced productivity.","category":"ai-spreadsheet","url":"http://simplemetrics.xyz","rating":5.0,"monthly_visits":4116,"pricing":{"type":"freemium"},"tags":["Gemini AI","AI Spreadsheet","AI","Google Sheets","Automation","Web Search","Productivity","AI Productivity Tools","AI Text Generator","Image Analysis","Add-on","Text Generation","AI Assistant","Data Extraction","AI For Data Analytics"],"features":["Features","analytics","Pricing","automation","ai_powered"]}