{"id":"11534","name":"Double A Framework: AI-Driven Innovation","description":"A framework to navigate and harness AI, blending AI, Agile, and Design Thinking.","category":"ai-project-management","url":"https://www.aithinking.se","rating":5.0,"monthly_visits":294,"pricing":{"type":"contact-for-pricing"},"tags":["AI Consulting","AI project management","AI strategy","AI Workflow","AI framework","Digital transformation","AI Copilot","AI Project Management","Design Thinking","Innovation","Agile"],"features":["Pricing","Features","ai_powered"]}