{"id":"11576","name":"AI Powered Image Upscaler","description":"AIImageUpscale.com enhances images using GAN technology, increasing resolution and quality up to 16K.","category":"ai-image-upscaler","url":"https://www.aiimageupscale.com","rating":5.0,"monthly_visits":601,"pricing":{"type":"freemium"},"tags":["Image clarity enhancer","AI upscaling","AI photo enlarger","Upscale photos","Enlarge photos","Photo upscaling","AI Photo Enhancer","AI Image Enhancer","Photo detail enhancer","Free online upscaler","Print-ready photos","Increase image resolution","AI Art Generator","Low-res to high-res","Super resolution","AI Image Upscaler","AI image upscaler","Sharpen images","Enhance photos","Online photo enhancer tool"],"features":["free","Pricing","Features","ai_powered"]}