{"id":"11700","name":"FloCareer","description":"FloCareer is an Interview-as-a-Service platform for efficient tech hiring.","category":"ai-recruiting","url":"https://www.flocareer.com","rating":5.0,"monthly_visits":173988,"pricing":{"type":"contact-for-pricing"},"tags":["AI Interview Assistant","Technical Interview","Video Interview","Interview Management","Fraud Prevention","AI Sourcing","AI For Data Analytics","Interview Outsourcing","Remote Hiring","AI Recruiting","Interview as a Service","Candidate Screening","On-demand Interviewers"],"features":["video_ai","Features","analytics","Pricing","ai_powered"]}