{"id":"12392","name":"Udio AI | Make your music","description":"Udio is an AI music generator that creates music from text descriptions in seconds.","category":"ai-music-generator","url":"https://www.udio.com","rating":5.0,"monthly_visits":2829109,"pricing":{"type":"free-trial"},"tags":["Generative music","AI Song Generator","AI song generator","Music creation","Text-to-music","AI music generator","AI generated music","Music sharing","AI Music Generator","AI music creator"],"features":["Pricing","Features","ai_powered"]}