{"id":"13082","name":"image Upscaling","description":"Free AI tool for image upscaling, generation, compression, and conversion.","category":"ai-image-upscaler","url":"https://imgupscaling.com","rating":5.0,"monthly_visits":0,"pricing":{"type":"free"},"tags":["AI Image Upscaling","Text to Image","AI Image Upscaler","AI Image Generator","Free Online Tool","Image Compression","Text-to-Image","Image Enlargement","AI Image Tool","AI Image Enhancer","Image Converter"],"features":["generative_ai","Features","free","Pricing","image_ai","ai_powered"]}