{"id":"1339","name":"Juice.ai","description":"Juice.ai automates marketing with AI-driven SEO blog posts for traffic and leads.","category":"ai-seo-tools","url":"https://juice.ai","rating":5.0,"monthly_visits":16276,"pricing":{"type":"paid"},"tags":["Blog posts","AI","Content marketing","Keyword research","SEO","Automation","Social media marketing","SEO Writing AI","AI Marketing Plan Generator","AI SEO Tools","Email capture","AI Blog Generator","AI Digital Marketing"],"features":["Pricing","Features","automation","ai_powered"]}