{"id":"1348","name":"Tactiq","description":"AI meeting assistant for live transcription, summaries, and actionable workflows on various platforms.","category":"ai-meeting-assistant","url":"https://tactiq.io/?via=wenhua","rating":5.0,"monthly_visits":3813577,"pricing":{"type":"freemium"},"tags":["AI Transcription","AI Meeting Assistant","Action items","Note-taking","Transcription tool","AI Note Taker","AI Summarizer","AI summaries","Speech to text","Meeting insights","Meeting transcription","Workflow integration","AI meeting assistant"],"features":["speech_ai","Pricing","Features","ai_powered"]}