{"id":"13596","name":"Zypher","description":"Zypher Assistant streamlines online communication with writing enhancement features.","category":"ai-writing-assistants","url":"https://chromewebstore.google.com/detail/zypher/jnffiijebiflabpekpfphicmifknpgep","rating":5.0,"monthly_visits":0,"pricing":{"type":"freemium"},"tags":["AI Writing","Paraphrasing","Writing Assistant","AI Paraphraser","Productivity","AI Grammar Checker","AI Summarizer","Email Enhancement","AI Youtube Summary","Grammar Checker","AI Email Assistant","Summarization","Communication Tool","AI Writing Assistants","Tone Adjustment"],"features":["Pricing","Features","ai_powered"]}