{"id":"13770","name":"LinkedIn Tech Recruiter SuperAssistant","description":"AI tool to personalize LinkedIn outreach for tech talent acquisition and pipeline building.","category":"ai-recruiting","url":"https://chromewebstore.google.com/detail/linkedin-tech-recruiter-s/dafblbbedmdhonaikmhgilaadhcbhcdl","rating":5.0,"monthly_visits":0,"pricing":{"type":"contact-for-pricing"},"tags":["AI recruiting","Recruitment automation","Candidate sourcing","Personalized messaging","AI Assistant","Talent pipeline","AI Lead Generation","AI Recruiting","LinkedIn outreach"],"features":["Pricing","Features","automation","ai_powered"]}