{"id":"13785","name":"OutreachGenius","description":"AI-powered LinkedIn outreach for personalized connections and increased engagement.","category":"ai-lead-generation","url":"https://chromewebstore.google.com/detail/outreachgenius/ekbmkecmfjahfomoafomalldaihhfjnh","rating":5.0,"monthly_visits":0,"pricing":{"type":"contact-for-pricing"},"tags":["AI","Networking","Personalization","Automation","AI Sales Assistant","AI Marketing","Recruiting","Lead generation","AI Lead Generation","LinkedIn outreach"],"features":["Pricing","Features","automation","ai_powered"]}