{"id":"13988","name":"Summarizing tool","description":"AI tool to summarize long texts.","category":"ai-summarizer","url":"https://chromewebstore.google.com/detail/summarizing-tool/mpiajopekdpckhpmkhnjadkdeganjgep","rating":5.0,"monthly_visits":0,"pricing":{"type":"free"},"tags":["AI Writing Assistants","Text summarizer","AI summarization","Content summarization","AI Summarizer","Article summarizer","AI Article Summarizer","Document summarization"],"features":["Pricing","Features","ai_powered"]}