{"id":"14568","name":"SYF-Apty Client","description":"Enhances user engagement with real-time navigation, guidance, and data correction.","category":"ai-copilot","url":"https://chromewebstore.google.com/detail/syf-apty-client/nepihmimcmflogaoaejjoeodldogidjk","rating":5.0,"monthly_visits":0,"pricing":{"type":"contact-for-pricing"},"tags":["Data entry correction","User engagement","Real-time guidance","Tips","AI Agent","User onboarding","Assistance","AI Copilot","AI Assistant","Navigation"],"features":["Pricing","Features","real_time","ai_powered"]}