{"id":"15662","name":"Semantic password generator","description":"Cloud GPU platform for AI image generation and diffusion models.","category":"other","url":"https://chromewebstore.google.com/detail/semantic-password-generat/jnihpommmhnofegpepjdbckgkhhjooln","rating":5.0,"monthly_visits":0,"pricing":{"type":"paid"},"tags":["Other","Cloud GPU","AI image generation","Machine learning","Virtual machine","Stable Diffusion"],"features":["generative_ai","Features","Pricing","image_ai","machine_learning","ai_powered"]}