{"id":"16379","name":"Magicshow 🪄","description":"Transform screen recordings into interactive AI-powered tutorials and demos.","category":"ai-tutorial","url":"https://chromewebstore.google.com/detail/magicshow-🪄/gkbekcoeckngpdplkcmlfpmbfhhjffha","rating":5.0,"monthly_visits":0,"pricing":{"type":"contact-for-pricing"},"tags":["Interactive learning","AI Video Recording","Interactive tutorials","Software tutorials","Product demos","AI Presentation Generator","AI Tutorial","AI-powered","Screen recording","Training materials"],"features":["Pricing","Features","video_ai","ai_powered"]}