{"id":"16412","name":"TextCortex: Personal AI Assistant & AI Writer","description":"TextCortex is an AI writing assistant that helps create authentic content efficiently.","category":"ai-writing-assistants","url":"https://chromewebstore.google.com/detail/textcortex-personal-ai-as/hahkojdegblcccihngmgndhdfheheofe","rating":5.0,"monthly_visits":0,"pricing":{"type":"freemium"},"tags":["AI Email Writer","Academic writing","AI Social Media Post Generator","Rewriting tool","Content creation","AI writing assistant","AI Blog Generator","AI Writing Assistants","AI Ad Generator","Social media content","AI Paraphraser","AI Summarizer","Readability checker","AI Rewriter","AI Translate","Email writing","AI Chatbot","Blog writing","Summarization tool","AI Copywriting","AI Text Generator","Ads & Marketing","Template library","Text-to-speech","Paraphrasing"],"features":["Features","chatbot","speech_ai","Pricing","ai_powered"]}