{"id":"17158","name":"QuraAi","description":"Qura.ai is a Chrome extension that uses AI to help you respond to tweets.","category":"ai-response-generator","url":"https://chromewebstore.google.com/detail/quraai/kejpbbehabekboaiagdmljaclbiafdpi","rating":5.0,"monthly_visits":0,"pricing":{"type":"free"},"tags":["AI Reply","AI","AI Response Generator","Social media","Social media management","Twitter","Automation","Tweet response","Chrome extension","AI Social Media Post Generator","AI Text Generator","AI Twitter","X"],"features":["Features","chrome_extension","browser_extension","Pricing","automation","ai_powered"]}