{"id":"17789","name":"PhotoRater","description":"AI-powered photo rating app providing analysis and feedback to improve appearance.","category":"ai-face-analyzer","url":"https://photorater.io","rating":5.0,"monthly_visits":6358,"pricing":{"type":"freemium"},"tags":["AI photo rater","Appearance improvement","Professional headshots","AI Face Analyzer","Social media selfies","Job interview photos","Fashion AI","AI Beauty","Image rating","Style feedback","Dating profile"],"features":["Pricing","Features","ai_powered"]}