{"id":"18178","name":"Dreamland: Create Kids Stories","description":"AI-powered storytelling app for kids to create, listen, and share stories.","category":"ai-story-generator","url":"https://www.storydreamland.com","rating":5.0,"monthly_visits":108,"pricing":{"type":"freemium"},"tags":["Digital storytelling","Kids stories","Interactive storybook","Educational storytelling","AI storytelling","AI Creative Writing","AI-powered stories","AI Story Generator","Story generator","AI Text Generator","Children's audio stories"],"features":["education","Pricing","Features","ai_powered"]}