{"id":"1829","name":"Silic AI","description":"AI-powered fashion design platform where users create and sell designs.","category":"ai-clothing-generator","url":"https://silic.ai","rating":5.0,"monthly_visits":0,"pricing":{"type":"contact-for-pricing"},"tags":["AI algorithms","Innovative designs","Direct to Fabric printing","AI T Shirt Design","AI fashion","Text to Image","Tencel","AI Clothing Generator","Marketplace","Modal","E-commerce","Fashion AI","Generative AI","Fashion design","Clothing","Fashion technology","Royalties"],"features":["generative_ai","Features","Pricing","image_ai","ai_powered"]}