{"id":"18352","name":"Haire.ai","description":"AI recruitment platform for efficient hiring and job searching.","category":"ai-recruiting","url":"https://haire.ai","rating":5.0,"monthly_visits":5613,"pricing":{"type":"freemium"},"tags":["AI interview","AI hiring","AI Avatar Video Generator","Candidate screening","AI recruitment","AI Chatbot","Talent acquisition","AI Job Description Generator","Recruitment platform","Job matching","AI Interview Assistant","AI Recruiting"],"features":["video_ai","Features","chatbot","Pricing","ai_powered"]}