{"id":"18739","name":"House of XYZ","description":"Full-service software studio specializing in AI and custom software development.","category":"ai-app-builder","url":"https://www.houseofxyz.com","rating":5.0,"monthly_visits":0,"pricing":{"type":"paid"},"tags":["custom apps","ai agent","ai chatbot","ai employees","AI Agent","AI Chatbot","software development","ai assistants","AI App Builder","AI Workflow","ai automation","prototypes","product development","full-service software studio","AI Research Tool","AI Assistant"],"features":["Features","chatbot","Pricing","automation","ai_powered"]}