{"id":"18825","name":"Zendesk AI (but cheaper)","description":"AI customer support agent automating 75% of support requests.","category":"ai-customer-service","url":"https://zendesk-ai-alternative.com","rating":5.0,"monthly_visits":0,"pricing":{"type":"freemium"},"tags":["AI Agent","Customer service","AI ticket tagging","Customer support automation","AI agent","AI chatbot","Zendesk integration","Live chat integration","AI customer support","AI Answer","AI Chatbot","Help desk","Freshchat integration","Ticket deflection","AI Customer Service","Intercom integration","AI Copilot","AI Assistant","AI Email Assistant"],"features":["Features","chatbot","Pricing","automation","ai_powered"]}