{"id":"18883","name":"Jobboardhub","description":"A collection of job boards for design, remote, and AI jobs.","category":"ai-jobs","url":"https://jobboardhub.one","rating":5.0,"monthly_visits":0,"pricing":{"type":"free"},"tags":["Big data jobs","Career","Remote jobs","AI jobs","AI Tools Directory","Machine learning jobs","Junior developer jobs","AI Jobs","Design jobs","Job board","Job search","Data science jobs","AI Recruiting"],"features":["Features","ai_powered","Pricing","machine_learning","developer"]}