{"id":"18932","name":"WeInstaReply","description":"All-in-one restaurant platform for online ordering and presence without commission fees.","category":"ai-website-builder","url":"https://weinstareply.com","rating":5.0,"monthly_visits":0,"pricing":{"type":"paid"},"tags":["Commission-free ordering","Restaurant website","Menu management","Customer loyalty","AI Advertising","Online ordering","AI Website Builder","QR code menu","Direct ordering","No-Code&Low-Code","Restaurant platform","AI promotions","AI Marketing"],"features":["Features","no_code","free","Pricing","ai_powered"]}