{"id":"19188","name":"globality.com","description":"AI-powered platform for autonomous sourcing and spend management.","category":"ai-agent","url":"https://globality.com","rating":5.0,"monthly_visits":44681,"pricing":{"type":"contact-for-pricing"},"tags":["Data-Driven Decisions","AI","Procurement","Autonomous Sourcing","AI Agent","AI Workflow","Tail Spend","Cost Reduction","Supplier Management","Enterprise Software","AI For Finance","Spend Management"],"features":["Pricing","enterprise","Features","ai_powered"]}