{"id":"19330","name":"rareconnections.io","description":"Rareconnections empowers content creators with AI tools for automation and monetization.","category":"ai-tools-directory","url":"https://rareconnections.io","rating":5.0,"monthly_visits":26205,"pricing":{"type":"freemium"},"tags":["AI","Repurposing","Content Creation","Monetization","AI Music Video Generator","AI Video Generator","Adobe Firefly","AI Tools Directory","Automation","AI Prompt Generator","Midjourney","AI Caption Generator","AI Dubbing","AI Tutorial","TikTok"],"features":["video_ai","Features","Pricing","automation","ai_powered"]}