{"id":"19384","name":"EmailFlow.ai - B2B Lead Generation","description":"AI-powered B2B lead generation and cold email automation platform.","category":"ai-email-marketing","url":"https://emailflow.ai","rating":5.0,"monthly_visits":0,"pricing":{"type":"contact-for-pricing"},"tags":["AI Email Generator","Email automation","AI Email Marketing","Email marketing","SMTP services","AI Agent","Sales automation","AI-driven cold email","AI Cold Calling","Email business data","B2B lead generation","AI Lead Generation","CRM integration","AI agents"],"features":["Features","Pricing","business","automation","ai_powered"]}