{"id":"19723","name":"Carryotic","description":"Productivity and social platform for workflow management and efficient communication.","category":"ai-project-management","url":"https://www.carryotic.com","rating":5.0,"monthly_visits":0,"pricing":{"type":"freemium"},"tags":["Social Platform","AI Task Management","Workflow","Team Communication","Collaboration","Productivity","Workspace","Notes","AI Project Management","AI Assistant","Task Management"],"features":["collaboration","Features","Pricing","team_features","ai_powered"]}