{"id":"20624","name":"Vidful.ai","description":"AI video generator transforming text and images into dynamic videos quickly and efficiently.","category":"ai-video-generator","url":"https://vidful.ai","rating":5.0,"monthly_visits":210807,"pricing":{"type":"freemium"},"tags":["AI video generator","Online video maker","Luma AI Dream Machine","AI Video Generator","Image to video","Text to Video","Kling AI","AI Animation Generator","Video creation","Image to Video","Text to video"],"features":["Pricing","Features","video_ai","ai_powered"]}