{"id":"20690","name":"Blureasy","description":"Free app to instantly blur faces/eyes in images and videos for privacy.","category":"ai-photo-editor","url":"https://blureasy.com","rating":5.0,"monthly_visits":0,"pricing":{"type":"freemium"},"tags":["free face blurring tool","blur faces in photos","high-quality image blur","image face blur","blur eyes in images","bulk image processing","AI Face Recognition","AI Video Editor","image protection software","blur faces in videos","video face blur","AI Photo Editor","bulk face blurring","face detection technology","photo privacy app","face blur","privacy app for images"],"features":["video_ai","Features","free","Pricing","ai_powered"]}