{"id":"21099","name":"Uwear.ai","description":"AI platform generating on-model clothing photos from flat-lay images, replacing traditional photoshoots.","category":"ai-models","url":"https://uwear.ai/?via=toolify","rating":5.0,"monthly_visits":55200,"pricing":{"type":"freemium"},"tags":["AI Realistic Image Generator","E-commerce photography","Flat-lay to on-model","Product image generation","AI model generation","AI fashion","AI Person Generator","Virtual try-on","AI Image Generator","AI API","Fashion AI","Fashion API","AI Models","AI Product Photography"],"features":["api_available","generative_ai","Features","Pricing","image_ai","ai_powered"]}