{"id":"21460","name":"Adobe Firefly AI Images Generator","description":"Generate AI images from custom prompts directly in your browser using Adobe Firefly AI.","category":"ai-image-generator","url":"https://chromewebstore.google.com/detail/adobe-firefly-ai-images-g/gokgnmfkonmjlakhlgbnmeeinhhkdoje","rating":5.0,"monthly_visits":0,"pricing":{"type":"freemium"},"tags":["Text-to-image","Adobe Firefly","Browser extension","AI image generation","Text to Image","AI Image Generator","AI Art Generator","Generative AI","AI art","Image creation"],"features":["generative_ai","Features","browser_extension","Pricing","image_ai","ai_powered"]}