{"id":"2155","name":"Elastic Bot","description":"Omnichannel AI chatbot platform for automated customer engagement and business automation.","category":"ai-chatbot","url":"https://www.elastic.ae","rating":5.0,"monthly_visits":0,"pricing":{"type":"free-trial"},"tags":["Omnichannel","WhatsApp chatbot","Customer support automation","AI Chatbot","AI Sales Assistant","Instagram chatbot","AI Customer Service","AI Social Media","AI chatbot","AI Instagram","Lead generation","Multilingual chatbot","AI Lead Generation","Live chat"],"features":["Features","chatbot","Pricing","automation","ai_powered"]}