{"id":"21744","name":"ClipWrite","description":"AI-powered tool to convert videos into blogs, social media posts, and articles.","category":"ai-repurpose","url":"https://www.clipwrite.com","rating":5.0,"monthly_visits":0,"pricing":{"type":"freemium"},"tags":["Video to LinkedIn post","Social media content creation","Content marketing tools","AI Speech-to-Text","YouTube transcription","AI Repurpose","AI content creation","SEO content creation","Content repurposing software","Video to Twitter thread","Video transcription services","Video to blog converter","AI-powered content generation","AI Social Media Post Generator","AI SEO Tools","AI Blog Generator","AI Transcription"],"features":["video_ai","Features","speech_ai","Pricing","ai_powered"]}