{"id":"22037","name":"Octoparse AI","description":"No-code platform to build custom AI workflows and RPA bots for automation.","category":"ai-app-builder","url":"https://www.octoparse.ai","rating":5.0,"monthly_visits":33468,"pricing":{"type":"freemium"},"tags":["AI Developer Tools","AI Robot","AI Web Scraping","AI Task Management","Workflow automation","AI automation","AI Social Media","Business automation","AI App Builder","No-code automation","Web scraping","Data extraction","AI Productivity Tools","No-Code&Low-Code","Process automation","AI Copilot","AI Lead Generation","RPA"],"features":["api_available","Features","no_code","automation","developer","ai_powered","Pricing","business"]}