{"id":"22544","name":"JetHire.ai - Efficient, Unbiased Hiring","description":"AI-powered platform for unbiased and efficient candidate screening and shortlisting.","category":"ai-recruiting","url":"https://jethire.ai","rating":5.0,"monthly_visits":0,"pricing":{"type":"contact-for-pricing"},"tags":["AI Recruiting","Objective Hiring","AI Resume Checker","GDPR Compliance","Talent Acquisition","Resume Screening","AI in HR","ATS Integration","AI Copilot","Bias Reduction","Recruitment","HR Automation","Candidate Screening"],"features":["Pricing","Features","automation","ai_powered"]}