{"id":"22837","name":"Tubefoster","description":"AI-powered Chrome extension for YouTube content creators to boost channel growth.","category":"ai-youtube","url":"https://chromewebstore.google.com/detail/tubefoster/maihkbihhdncciopnkkccglnadhpdgle","rating":5.0,"monthly_visits":0,"pricing":{"type":"freemium"},"tags":["AI Subtitle Generator","AI Content Generation","Chapter Editor","YouTube SEO","AI Title Generator","AI YouTube","Keyword Research","AI Description Generator","Video Translation","AI Translate","AI SEO Tools","Subtitle Translation","Chrome Extension","Video Optimization"],"features":["video_ai","Features","chrome_extension","browser_extension","Pricing","ai_powered"]}