{"id":"23172","name":"RankChase","description":"Platform for automated backlink exchanges and brand mentions to boost SEO and GEO.","category":"ai-seo-tools","url":"https://rankchase.com/?ref=toolifyq5","rating":5.0,"monthly_visits":2289,"pricing":{"type":"freemium"},"tags":["Backlink exchange","SEO","GEO","Link building","Domain Rating","Niche websites","Brand mentions","AI SEO Tools","Link exchange platform","SEO tools","AI Lead Generation","AI Digital Marketing"],"features":["Pricing","Features","ai_powered"]}