{"id":"23325","name":"Vibrant.ink","description":"AI-powered storytelling platform for creating captivating stories with images.","category":"ai-story-generator","url":"https://vibrant.ink","rating":5.0,"monthly_visits":0,"pricing":{"type":"freemium"},"tags":["Publishing","Writing tools","Creative writing","AI Illustration Generator","Story generation","Collaboration","AI Character","Writing platform","AI Plot Generator","Story creation","Character development","AI Creative Writing","Storytelling","World building","AI writing assistant","AI Story Generator","Image generation"],"features":["collaboration","generative_ai","Features","Pricing","image_ai","ai_powered"]}