{"id":"23539","name":"Professor Blue","description":"AI tool for Bluesky post analysis and audience growth.","category":"ai-social-media","url":"https://professor.blue","rating":5.0,"monthly_visits":0,"pricing":{"type":"free"},"tags":["Bluesky followers","Bluesky audience growth","Bluesky creator growth","Social media analytics","AI Social Media","Bluesky post optimization","Bluesky engagement","AI for Bluesky","Bluesky posting tips","Bluesky analytics","AI Assistant","AI Marketing"],"features":["Pricing","analytics","Features","ai_powered"]}