{"id":"23912","name":"Indian Wedding AI","description":"AI tool to visualize and plan Indian, Pakistani, and South Asian weddings with custom visuals.","category":"ai-design-generator","url":"https://www.indianweddingai.com","rating":5.0,"monthly_visits":0,"pricing":{"type":"paid"},"tags":["AI Realistic Image Generator","Cultural wedding","Desi wedding","Wedding planning","AI wedding generator","Wedding visualization","AI Image Generator","AI Design Generator","South Asian wedding","AI design","AI Art Generator","Pakistani wedding","Indian wedding"],"features":["Pricing","Features","ai_powered"]}