{"id":"23946","name":"StencilFrame","description":"StencilFrame: AI-powered platform for automatic software documentation and workflow capture.","category":"ai-knowledge-base","url":"https://stencilframe.io","rating":5.0,"monthly_visits":0,"pricing":{"type":"paid"},"tags":["Compliance Auditing","AI Knowledge Management","AI Documentation","AI Documents Generator","Documentation Automation","Product Training","User Experience Monitoring","Content Generation","AI Content Detector","Product Knowledge","Workflow Capture","AI Knowledge Base","Self-Service Support"],"features":["Pricing","Features","automation","ai_powered"]}