{"id":"23960","name":"Nutritionista","description":"All-in-one nutrition app with personalized meal plans and AI-powered features.","category":"ai-fitness","url":"https://apps.apple.com/us/app/nutritionista-calorie-counter/id6670344419","rating":5.0,"monthly_visits":0,"pricing":{"type":"freemium"},"tags":["Nutrition","Health tracking","AI Fitness","Weight loss","AI Recipe","Hydration","Fitness","AI nutrition","Diet","Meal planning","AI Cooking Assistant","AI Scanner","Calorie counter","Recipe generator"],"features":["Pricing","Features","ai_powered"]}