{"id":"25769","name":"PingFuse","description":"Instant Upwork job notifications with custom filters and multi-channel alerts.","category":"ai-assistant","url":"https://pingfuse.com","rating":5.0,"monthly_visits":0,"pricing":{"type":"freemium"},"tags":["Upwork alerts","AI Writing Assistants","Telegram notifications","AI proposal generator","Upwork automation","Slack notifications","Email notifications","AI Lead Generation","Job finder","Job alerts","AI Productivity Tools","Browser notifications","AI Assistant","Freelance jobs","Upwork notifications"],"features":["Features","free","Pricing","automation","ai_powered"]}