{"id":"2581","name":"Lingobo","description":"AI-powered English conversation practice for professionals and companies.","category":"ai-language-learning","url":"https://lingobo.com","rating":5.0,"monthly_visits":0,"pricing":{"type":"freemium"},"tags":["AI English tutor","Micro-learning","AI Coaching","Professional English","Language learning","AI Language Learning","AI Speech Recognition","English conversation practice","AI-powered learning","AI Text-to-Speech"],"features":["speech_ai","Pricing","Features","ai_powered"]}