{"id":"26140","name":"Greetigo","description":"Greetigo is a desktop app for AI-powered reminders and personalized greetings for important dates.","category":"ai-message-generator","url":"https://greetigo.com","rating":5.0,"monthly_visits":0,"pricing":{"type":"freemium"},"tags":["Personalized Messages","AI Message Generator","Anniversary Reminders","Reminders","Birthday Reminders","AI Greetings","Desktop App","Event Tracking","AI Calendar","AI Assistant","Slack Integration"],"features":["Pricing","Features","ai_powered"]}