{"id":"26159","name":"Gumloop","description":"No-code platform for building and hosting AI-powered business automations.","category":"ai-workflow","url":"https://www.gumloop.com","rating":5.0,"monthly_visits":372931,"pricing":{"type":"freemium"},"tags":["AI","AI Web Scraping","SEO","automation","AI Workflow","web scraping","AI Agent","social media","workflow","document processing","No-Code&Low-Code","business automation","no-code","integration"],"features":["api_available","Features","no_code","Pricing","business","automation","ai_powered"]}