{"id":"26305","name":"Image to Text  CC","description":"Online OCR service to extract text from images and convert to various formats.","category":"ai-ocr","url":"https://www.imagetotext.cc","rating":5.0,"monthly_visits":303649,"pricing":{"type":"freemium"},"tags":["AI","AI Document Extraction","AI Image Recognition","PDF to Excel","Batch Processing","Image Translator","Image to Excel","Machine Learning","Image Conversion","Document Digitization","Image to Text","Text Extraction","Data Entry","AI OCR","OCR"],"features":["Pricing","Features","machine_learning","ai_powered"]}