{"id":"26497","name":"MyDesigns.io","description":"All-in-one platform for print on demand and digital product businesses.","category":"ai-design-generator","url":"https://affiliates.mydesigns.io/32714/153495","rating":5.0,"monthly_visits":124527,"pricing":{"type":"freemium"},"tags":["AI","Digital Products","Product Design","Print on Demand","Amazon","AI Product Description Generator","AI Productivity Tools","AI Background Remover","Bulk Processing","Etsy","Automation","E-commerce","AI Art Generator","Order Fulfillment","AI T Shirt Design","AI Title Generator","Shopify","AI Mockup Generator","AI Image Upscaler","AI Design Generator","Mockups"],"features":["Pricing","Features","automation","ai_powered"]}