{"id":"26739","name":"Cross-Image Annotation by T-Rex Label","description":"AI-powered image annotation tool for computer vision datasets.","category":"ai-developer-tools","url":"https://www.trexlabel.com","rating":5.0,"monthly_visits":2771,"pricing":{"type":"free"},"tags":["Object detection","AI Developer Tools","AI Detector","AI Image Recognition","Computer vision","Dataset creation","Labelbox","Data labeling","Roboflow","COCO dataset","YOLO dataset","AI Productivity Tools","Zero-shot object detection","AI Models","AI image annotation","AI Assistant","Grounding DINO"],"features":["Pricing","Features","ai_powered","developer"]}