{"id":"3786","name":"summarygenerator.ai","description":"Free AI-powered online text summarizer for concise summaries.","category":"ai-summarizer","url":"https://summarygenerator.ai","rating":5.0,"monthly_visits":177,"pricing":{"type":"free"},"tags":["AI Writing Assistants","Text summarizer","Summary generator","AI summarizer","Text condensation","Content summarization","Online summarizer","Document summarizer","AI Summarizer","AI Productivity Tools","AI Text Generator","Free summarizer","Article summarizer","AI Article Summarizer"],"features":["free","Pricing","Features","ai_powered"]}