{"id":"3837","name":"Oscar personal bedtime stories","description":"Personalized bedtime stories app using AI to create unique adventures for children.","category":"ai-story-generator","url":"https://apps.apple.com/app/apple-store/id1663618939","rating":5.0,"monthly_visits":0,"pricing":{"type":"freemium"},"tags":["AI Story Generator","Audiobooks","Moral lessons","Children's education","Bedtime stories","AI Creative Writing","AI Text-to-Speech","AI story generator","Personalized stories","Kids app","AI Text Generator"],"features":["Features","education","Pricing","speech_ai","ai_powered"]}