{"id":"3868","name":"LingoChamp","description":"AI-powered language learning platform with personalized courses and real-time practice.","category":"ai-language-learning","url":"https://www.lingochamp.world","rating":5.0,"monthly_visits":1069,"pricing":{"type":"free-trial"},"tags":["Online language courses","Native English tutors","Chat community","English learning","Language learning","AI coach","Personalized learning","AI Language Learning","AI Assistant","AI-powered learning","Spanish learning"],"features":["Pricing","Features","ai_powered"]}