{"id":"3920","name":"Iterate.World","description":"A collaborative platform for AI image generation with multiple engines and daily games.","category":"ai-art-generator","url":"https://iterate.world","rating":5.0,"monthly_visits":0,"pricing":{"type":"freemium"},"tags":["Openjourney","AI image generation","Collaboration","AI Image Generator","Daily games","AI Art Generator","Image streams","Prompts","DALL-E 2","Stable Diffusion"],"features":["collaboration","generative_ai","Features","Pricing","image_ai","ai_powered"]}