{"id":"4734","name":"RestoGPT AI","description":"AI-powered online ordering storefront builder for restaurants, converting orders into loyal customers.","category":"ai-website-builder","url":"https://restogpt.ai","rating":5.0,"monthly_visits":3223,"pricing":{"type":"free-trial"},"tags":["AI","Restaurant","Marketing","Menu management","Automation","CRM","Online ordering","AI Website Builder","Storefront","Delivery","AI Design Generator"],"features":["Pricing","Features","automation","ai_powered"]}