{"id":"4982","name":"Asinstant","description":"AI-powered business assistant for growth, customer support, and marketing management.","category":"ai-customer-service","url":"https://asinstant.com","rating":5.0,"monthly_visits":234,"pricing":{"type":"paid"},"tags":["AI","Chatbot","Lead Generation","Website","Google","WhatsApp","AI Chatbot","Automation","Multi-channel","CRM","Business Assistant","Data Analytics","Customer Support","Marketing","Messenger","Instagram","AI Customer Service","AI Assistant","AI Marketing"],"features":["Features","chatbot","analytics","Pricing","business","automation","ai_powered"]}