{"id":"4998","name":"Instancy","description":"All-in-one learning platform with AI, AR, and VR for business growth.","category":"ai-course","url":"https://instancy.com","rating":5.0,"monthly_visits":5230,"pricing":{"type":"contact-for-pricing"},"tags":["Content management","LMS","Training","eCommerce","AI Course","eLearning","VR learning","AI Chatbot","LCMS","Chatbot","No-Code&Low-Code","Learning platform","AR learning","LXP","Mobile learning","AI learning","AI Writing Assistants","LRS"],"features":["Features","chatbot","no_code","Pricing","ai_powered"]}