{"id":"5328","name":"RaqiAI","description":"RaqiAI empowers businesses with design, marketing, and coding expertise for growth and success.","category":"ai-consulting","url":"https://www.raqiai.com","rating":5.0,"monthly_visits":0,"pricing":{"type":"paid"},"tags":["Middle East marketing","Coding services","AI integration","No-Code&Low-Code","AI For Data Analytics","Data analytics","Design agency","AI Advertising","Marketing agency","E-commerce","Web design","Mobile app development","AI Digital Marketing","AI Consulting","AI Writing","Branding","AI Graphic Design","AI Website Designer","Social media marketing","AI Marketing"],"features":["Features","analytics","no_code","Pricing","mobile_app","ai_powered"]}