{"id":"5420","name":"Sauce","description":"AI product feedback engine for consolidating feedback and automating insights.","category":"ai-product-manager","url":"https://sauce.app","rating":5.0,"monthly_visits":6648,"pricing":{"type":"contact-for-pricing"},"tags":["AI","AI Product Manager","Automation","Team alignment","AI Summarizer","Linear integration","AI Productivity Tools","AI Assistant","Customer insights","Feedback management","Jira integration","AI Research Tool","Slack integration","Release management","Product feedback","AI For Data Analytics"],"features":["collaboration","Features","analytics","Pricing","team_features","automation","ai_powered"]}