{"id":"6181","name":"TopWriter","description":"TopwriterX: Automated writing solutions and premium backlink services to elevate your brand.","category":"ai-writing","url":"https://topwriter.co","rating":5.0,"monthly_visits":0,"pricing":{"type":"paid"},"tags":["AI Writing","Advertising","Marketing automation","SEO","Email marketing","Backlinks","Social media marketing","Landing pages","AI Content Detector","AI writing","AI Copywriting","Content writing"],"features":["Pricing","Features","automation","ai_powered"]}