{"id":"7342","name":"FunBlocks AI","description":"All-in-one AI workspace for writing, learning, mind mapping, and creating diverse content.","category":"ai-mind-mapping","url":"https://funblocks.net","rating":5.0,"monthly_visits":22239,"pricing":{"type":"free-trial"},"tags":["AI slides","AI Writing Assistants","AI Documents Generator","Learning","AI Tools Directory","Brainstorming","AI Mind Mapping","AI Image Generator","Productivity","AI Productivity Tools","AI assistant","AI Presentation Generator","AI writing","AI Youtube Summary","AI tools","AI workspace","Mind mapping","AI Infographic Generator"],"features":["Pricing","Features","ai_powered"]}