{"id":"7486","name":"MAIA - My AI Assistant","description":"MAIA is an AI assistant Chrome extension for voice transcription and content manipulation.","category":"ai-assistant","url":"https://www.chromeaiextn.com","rating":5.0,"monthly_visits":575,"pricing":{"type":"paid"},"tags":["AI Speech-to-Text","AI Browsers","Text simplification","Voice transcription","AI Transcriber","Speech-to-text","Chrome extension","Content summarization","AI Summarizer","AI Translate","AI Text Generator","Translation","Generative AI","Content generation","AI Assistant","AI assistant"],"features":["Features","chrome_extension","browser_extension","speech_ai","Pricing","voice_ai","ai_powered"]}