{"id":"7524","name":"Vetted AI","description":"A shopping assistant that compares reviews, prices, and tracks sales across merchants.","category":"ai-shopping-assistant","url":"https://vetted.ai","rating":5.0,"monthly_visits":71605,"pricing":{"type":"free"},"tags":["AI Reviews","Shopping assistant","Sale alerts","Reddit reviews","Review aggregation","Price comparison","AI Shopping Assistant","YouTube reviews","Product research","Expert reviews","AI Research Tool"],"features":["Pricing","Features","ai_powered"]}