{"id":"7734","name":"MAXP","description":"Gamified online education platform teaching future job skills to students in grades 8-11.","category":"ai-course","url":"https://www.maxp.io","rating":5.0,"monthly_visits":1573,"pricing":{"type":"freemium"},"tags":["Interactive learning","Gamified learning","AI Coaching","Entrepreneurship","AI Teachers","Online education","Personal development","Career development","Future skills","E-learning","AI Course"],"features":["education","Pricing","Features","ai_powered"]}