{"id":"8464","name":"Fancinet","description":"AI platform for image generation, modification, and branded content creation.","category":"ai-image-generator","url":"https://www.deepvinci.ai","rating":5.0,"monthly_visits":643,"pricing":{"type":"freemium"},"tags":["Text-to-image","AI image editor","Branded content","AI image generation","Text to Image","AI Image Generator","Artificial intelligence","Image-to-image","Generative AI","Image to Image"],"features":["generative_ai","Features","Pricing","image_ai","ai_powered"]}