{"id":"9431","name":"Peeksta","description":"E-commerce tool to discover winning products and ads through competitor analysis.","category":"ai-advertising","url":"https://peeksta.com/amember/aff/go/toolify","rating":5.0,"monthly_visits":11580,"pricing":{"type":"free-trial"},"tags":["TikTok ads","Competitor analysis","Ad spy","AI Sales","Ad tracking","AI Advertising","E-commerce","AI Facebook","AI Tiktok","AI Data Mining","Product research","Facebook ads","AI Research Tool","Dropshipping","Trending products","AI Digital Marketing","AI Marketing"],"features":["Pricing","Features","ai_powered"]}