{"id":"9759","name":"Nutrition Assistant","description":"Personalized nutrition guide with tailored advice, recipes, and meal plans for a healthier lifestyle.","category":"ai-assistant","url":"https://nutritionassistant.app","rating":5.0,"monthly_visits":0,"pricing":{"type":"free"},"tags":["Nutrition","Meal Plans","Weight Loss","Health","AI Recipe","AI Chatbot","Food Intolerances","AI Nutrition Assistant","Wellness","AI Cooking Assistant","Personalized Nutrition","Recipes","AI Assistant","Dietary Advice"],"features":["chatbot","Pricing","Features","ai_powered"]}