{"id":"9782","name":"Naria AI","description":"Naria is a platform for creating and sharing illustrated children's stories.","category":"ai-story-generator","url":"https://www.naria.ai","rating":5.0,"monthly_visits":4226,"pricing":{"type":"freemium"},"tags":["Digital books","Literacy","Audiobooks","Creative writing","AI Avatar Generator","AI Illustration Generator","Children's stories","Family activities","AI Creative Writing","Storytelling","Education","Personalized stories","AI Story Generator","AI Book Writing"],"features":["education","Pricing","Features","ai_powered"]}