{"id":"9854","name":"BlipCut AI Video Translator","description":"AI-powered video translation tool supporting 130+ languages with lip sync and voice cloning.","category":"ai-video-translator","url":"https://videotranslator.blipcut.com","rating":5.0,"monthly_visits":601846,"pricing":{"type":"paid"},"tags":["AI Voice Cloning","AI Subtitle Generator","subtitle translator","lip sync","ai translator","AI Lip Sync Generator","AI Video Translator","ai video translator","voice cloning","video translator","long video to shorts","video dubbing","AI Voice Translator","audio translation","translate video","AI Dubbing","youtube transcript","ai clip maker"],"features":["video_ai","Features","Pricing","voice_ai","ai_powered"]}